monodiff
