Metadata-Version: 1.2
Name: mono-diff
Version: 0.1.8
Summary: UNKNOWN
Home-page: https://github.com/ran729/mono
Author: Ran Sasportas
Author-email: ran729@gmail.com
License: MIT
Platform: UNKNOWN
Requires-Python: >=3.7
